test/and.py
test/enjoy.py
test/hear.py
test/model.py
test/those.py
xy_file/Manager.py
xy_file/Runner.py
xy_file/__init__.py
xy_file/types.py
xy_file/utils.py
xy_file/Object/File.py
xy_file/Object/Permission.py
xy_file/Object/__init__.py
xy_file/Operation/Rename.py
xy_file/Operation/Search.py
xy_file/Operation/__init__.py
xy_file/execute/Main.py
xy_file/execute/__init__.py
xy_file-1.0.7.dist-info/LICENSE
xy_file-1.0.7.dist-info/METADATA
xy_file-1.0.7.dist-info/WHEEL
xy_file-1.0.7.dist-info/entry_points.txt
xy_file-1.0.7.dist-info/top_level.txt
xy_file-1.0.7.dist-info/RECORD
