Metadata-Version: 2.1
Name: xy_file
Version: 1.0.7
Summary: 文件相关处理模块
Author-email: 余洋 <yuyangit.0515@qq.com>
Classifier: Programming Language :: Python :: 3
Requires-Python: >=3.11.3
License-File: LICENSE
Requires-Dist: rich
Requires-Dist: faker
Requires-Dist: xy_argparse
Requires-Dist: xy_console
